bodycal/__init__.py
bodycal-0.0.7.dist-info/LICENSE.txt
bodycal-0.0.7.dist-info/METADATA
bodycal-0.0.7.dist-info/WHEEL
bodycal-0.0.7.dist-info/top_level.txt
bodycal-0.0.7.dist-info/RECORD
