Metadata-Version: 2.1
Name: bodycal
Version: 0.0.7
Summary: Physical calculater functions
Home-page: https://github.com/gncll/body-calculator
Author: Gencay Isik
Author-email: bilinclizihin@gmail.com
License: MIT
Keywords: calculator
Platform: UNKNOWN
Classifier: Development Status :: 5 - Production/Stable
Classifier: Intended Audience :: Education
Classifier: Operating System :: OS Independent
Classifier: License :: OSI Approved :: MIT License
Classifier: Programming Language :: Python :: 3
License-File: LICENSE.txt
Requires-Dist: numpy
